{"GlobalPropertiesHash":"uPsJxZzFJRH69F510uxNNbXxUpJhwe8y+WF5NH4UBEI=","FingerprintPatternsHash":"gq3WsqcKBUGTSNle7RKKyXRIwh7M8ccEqOqYvIzoM04=","PropertyOverridesHash":"8ZRc1sGeVrPBx4lD717BgRaQekyh78QKV9SKsdt638U=","InputHashes":["Mre56hmRO3c0oYXaKDnQrPm0dUs5PfdbIcSIJKBveIk=","xWTgih62DBiu2J2WYi5zM\u002B5FDG3sZisifAITQZt3UAs=","Idmzt\u002BhlmTFH2zGj0rxtIMqOo7aQZpRG9Rik9PcH\u002BR8=","qdriMpfVUdp2Ljn250oL3neQnDZ36fDHvt202iLUoVw=","BOrMCnlxZDqjsGQz5Yu1mY/SPsC4AeXjbeqLZDp5\u002By8=","i2qxlZi86QJ6dTbhpwp1ASSiJjD6iCUMHiTRhUYGh0I="],"CachedAssets":{"Mre56hmRO3c0oYXaKDnQrPm0dUs5PfdbIcSIJKBveIk=":{"Identity":"C:\\Users\\elif\\source\\repos\\HSD_quiz_web\\HSD_quiz_web\\wwwroot\\admin.html","SourceId":"HSD_quiz_web","SourceType":"Discovered","ContentRoot":"C:\\Users\\elif\\source\\repos\\HSD_quiz_web\\HSD_quiz_web\\wwwroot\\","BasePath":"_content/HSD_quiz_web","RelativePath":"admin#[.{fingerprint}]?.html","AssetKind":"All","AssetMode":"All","AssetRole":"Primary","AssetMergeBehavior":null,"AssetMergeSource":"","RelatedAsset":null,"AssetTraitName":null,"AssetTraitValue":null,"Fingerprint":"5xt15yadmp","Integrity":"R\u002BXagRbvRdHrNY6h1QMqzgeloAxTKTzcwHcYbW0szTo=","CopyToOutputDirectory":"Never","CopyToPublishDirectory":"PreserveNewest","OriginalItemSpec":"wwwroot\\admin.html","FileLength":38690,"LastWriteTime":"2026-06-26T17:22:44.305357+00:00"},"xWTgih62DBiu2J2WYi5zM\u002B5FDG3sZisifAITQZt3UAs=":{"Identity":"C:\\Users\\elif\\source\\repos\\HSD_quiz_web\\HSD_quiz_web\\wwwroot\\hsd-logo (1).png","SourceId":"HSD_quiz_web","SourceType":"Discovered","ContentRoot":"C:\\Users\\elif\\source\\repos\\HSD_quiz_web\\HSD_quiz_web\\wwwroot\\","BasePath":"_content/HSD_quiz_web","RelativePath":"hsd-logo (1)#[.{fingerprint}]?.png","AssetKind":"All","AssetMode":"All","AssetRole":"Primary","AssetMergeBehavior":null,"AssetMergeSource":"","RelatedAsset":null,"AssetTraitName":null,"AssetTraitValue":null,"Fingerprint":"w4bppga59q","Integrity":"YCJkIktPvfmsQtIFxzLC6qLQexmprfCmEtaOL3zaLBg=","CopyToOutputDirectory":"Never","CopyToPublishDirectory":"PreserveNewest","OriginalItemSpec":"wwwroot\\hsd-logo (1).png","FileLength":32201,"LastWriteTime":"2026-06-26T16:27:44.7644434+00:00"},"Idmzt\u002BhlmTFH2zGj0rxtIMqOo7aQZpRG9Rik9PcH\u002BR8=":{"Identity":"C:\\Users\\elif\\source\\repos\\HSD_quiz_web\\HSD_quiz_web\\wwwroot\\hsd-logo-white.png","SourceId":"HSD_quiz_web","SourceType":"Discovered","ContentRoot":"C:\\Users\\elif\\source\\repos\\HSD_quiz_web\\HSD_quiz_web\\wwwroot\\","BasePath":"_content/HSD_quiz_web","RelativePath":"hsd-logo-white#[.{fingerprint}]?.png","AssetKind":"All","AssetMode":"All","AssetRole":"Primary","AssetMergeBehavior":null,"AssetMergeSource":"","RelatedAsset":null,"AssetTraitName":null,"AssetTraitValue":null,"Fingerprint":"0hps8np3uw","Integrity":"9IMn57VMYV9D\u002BgikwfkioUO\u002BnvgnJM7sloCPOJ6jVe0=","CopyToOutputDirectory":"Never","CopyToPublishDirectory":"PreserveNewest","OriginalItemSpec":"wwwroot\\hsd-logo-white.png","FileLength":30328,"LastWriteTime":"2026-06-26T16:27:25.0813894+00:00"},"qdriMpfVUdp2Ljn250oL3neQnDZ36fDHvt202iLUoVw=":{"Identity":"C:\\Users\\elif\\source\\repos\\HSD_quiz_web\\HSD_quiz_web\\wwwroot\\index.html","SourceId":"HSD_quiz_web","SourceType":"Discovered","ContentRoot":"C:\\Users\\elif\\source\\repos\\HSD_quiz_web\\HSD_quiz_web\\wwwroot\\","BasePath":"_content/HSD_quiz_web","RelativePath":"index#[.{fingerprint}]?.html","AssetKind":"All","AssetMode":"All","AssetRole":"Primary","AssetMergeBehavior":null,"AssetMergeSource":"","RelatedAsset":null,"AssetTraitName":null,"AssetTraitValue":null,"Fingerprint":"o7tpkegojb","Integrity":"JOwtaSuC\u002BpQDL2G/bRJBKVvcYI4Hl16tYI46TbaKftw=","CopyToOutputDirectory":"Never","CopyToPublishDirectory":"PreserveNewest","OriginalItemSpec":"wwwroot\\index.html","FileLength":18794,"LastWriteTime":"2026-06-26T17:04:56.3260122+00:00"}},"CachedCopyCandidates":{}}